{"Includes":["import \"math/big\""],"Defines":["const (\n\tgeo_r3_prec = big.MaxPrec\n)"],"TypeDefs":[],"Globals":["var ()"],"Structs":["type geo_r3_Vector struct {\n\tX, Y, Z float64\n}","type geo_r3_PreciseVector struct {\n\tX, Y, Z *big.Float\n}"],"Function Declarations":["","",""],"Function Implementations":["func geo_r3_precFloat(f float64) *big.Float {\n\treturn new(big.Float).SetPrec(geo_r3_prec).SetFloat64(f)\n}","func geo_r3_NewPreciseVector(x, y, z float64) geo_r3_PreciseVector {\n\treturn geo_r3_PreciseVector{\n\t\tX: geo_r3_precFloat(x),\n\t\tY: geo_r3_precFloat(y),\n\t\tZ: geo_r3_precFloat(z),\n\t}\n}","func geo_r3_PreciseVectorFromVector(v geo_r3_Vector) geo_r3_PreciseVector {\n\treturn geo_r3_NewPreciseVector(v.X, v.Y, v.Z)\n}"],"Enums":[]}
